TranslationsServer-0.1.1.dist-info/DESCRIPTION.rst
TranslationsServer-0.1.1.dist-info/METADATA
TranslationsServer-0.1.1.dist-info/RECORD
TranslationsServer-0.1.1.dist-info/WHEEL
TranslationsServer-0.1.1.dist-info/metadata.json
TranslationsServer-0.1.1.dist-info/top_level.txt
translations_server/__init__.py
translations_server/db.py
translations_server/server.py
translations_server/lib/__init__.py
translations_server/lib/postgres_db.py
