Metadata-Version: 2.0
Name: TranslationsServer
Version: 0.1.1
Summary: The translations service server
Home-page: https://github.com/GreenelyAB/TranslationsServer
Author: GreenelyAB
Author-email: info@greenely.com
License: MIT
Keywords: store manage translation translations server internationalization
Platform: UNKNOWN
Classifier: Development Status :: 5 - Production/Stable
Classifier: Intended Audience :: Developers
Classifier: Topic :: Communications
Classifier: Topic :: Software Development :: Internationalization
Classifier: Topic :: Software Development :: Localization
Classifier: Topic :: Text Processing
Classifier: License :: OSI Approved :: MIT License
Classifier: Programming Language :: Python :: 3.5
Requires-Dist: DBQuery (>=0.3.1)
Requires-Dist: psycopg2 (>=2.6.1)
Requires-Dist: pyzmq (>=15.2.0)
